MANIFEST.in
README.rst
setup.py
SemanticAnalysis/__init__.py
SemanticAnalysis/__init__.pyc
SemanticAnalysis.egg-info/PKG-INFO
SemanticAnalysis.egg-info/SOURCES.txt
SemanticAnalysis.egg-info/dependency_links.txt
SemanticAnalysis.egg-info/top_level.txt
SemanticAnalysis.egg-info/zip-safe
SemanticAnalysis/CNSentimentAnalysis/__init__.py
SemanticAnalysis/CNSentimentAnalysis/__init__.pyc
SemanticAnalysis/CNSentimentAnalysis/Algorithms/algorithm.py
SemanticAnalysis/CNSentimentAnalysis/Algorithms/algorithm.pyc
SemanticAnalysis/CNSentimentAnalysis/Algorithms/bsa_algorithm.py
SemanticAnalysis/CNSentimentAnalysis/Algorithms/bsa_algorithm.pyc
SemanticAnalysis/CNSentimentAnalysis/CNArticleAnalysis/__init__.py
SemanticAnalysis/CNSentimentAnalysis/CNArticleAnalysis/__init__.pyc
SemanticAnalysis/CNSentimentAnalysis/CNArticleAnalysis/article_analysis.py
SemanticAnalysis/CNSentimentAnalysis/CNArticleAnalysis/article_analysis.pyc
SemanticAnalysis/CNSentimentAnalysis/CNArticleAnalysis/gen_file.py
SemanticAnalysis/CNSentimentAnalysis/CNArticleAnalysis/new.txt
SemanticAnalysis/CNSentimentAnalysis/CNArticleAnalysis/test.txt
SemanticAnalysis/CNSentimentAnalysis/CNParticipation/__init__.py
SemanticAnalysis/CNSentimentAnalysis/CNParticipation/jieba_participator.py
SemanticAnalysis/CNSentimentAnalysis/CNParticipation/jieba_participator.pyc
SemanticAnalysis/CNSentimentAnalysis/DUTLib/__init__.py
SemanticAnalysis/CNSentimentAnalysis/DUTLib/dut_extractor.py
SemanticAnalysis/CNSentimentAnalysis/DUTLib/dut_extractor.pyc
SemanticAnalysis/CNSentimentAnalysis/DUTLib/dut_extractor_factory.py
SemanticAnalysis/CNSentimentAnalysis/DUTLib/dut_extractor_factory.pyc
SemanticAnalysis/CNSentimentAnalysis/DUTLib/dut_sentiment_words.csv
SemanticAnalysis/CNSentimentAnalysis/DUTLib/readme.txt
SemanticAnalysis/CNSentimentAnalysis/common/__init__.py
SemanticAnalysis/CNSentimentAnalysis/common/__init__.pyc
SemanticAnalysis/CNSentimentAnalysis/common/log_tool.py
SemanticAnalysis/CNSentimentAnalysis/common/log_tool.pyc
SemanticAnalysis/CNSentimentAnalysis/common_lib/negative_words.txt
SemanticAnalysis/CNSentimentAnalysis/hownet_lib/degree_words.txt
