Metadata-Version: 1.1
Name: SemanticAnalysis
Version: 0.0.4
Summary: This package can do the Chinese semantic analysis.
Home-page: https://bitbucket.org/shichaoqu/semantic-analysis-tool/overview
Author: qushichao
Author-email: 578312618@qq.com
License: MIT
Keywords: semantic analysis Chinese
Platform: UNKNOWN
Classifier: License :: OSI Approved :: MIT License
Classifier: Programming Language :: Python
Classifier: Intended Audience :: Developers
Classifier: Operating System :: OS Independent
